[
  {
    "annual": 27.95460725161938,
    "dd": 44.759878169784415,
    "win": 12.195121951219512,
    "pf": 13.658962562641323,
    "trades": 82,
    "total": 721.6147958728907,
    "final": 82161.47958728907,
    "config": {
      "name": "ETH+ 动态仓位 + 止盈 200%",
      "stop": 0.05,
      "tp": 2.0,
      "trail": 0.5,
      "trail_after": 0.5,
      "dynamic": true
    }
  },
  {
    "annual": 27.95460725161938,
    "dd": 44.759878169784415,
    "win": 12.195121951219512,
    "pf": 13.658962562641323,
    "trades": 82,
    "total": 721.6147958728907,
    "final": 82161.47958728907,
    "config": {
      "name": "ETH+ 固定仓位 + 止盈 200%",
      "stop": 0.05,
      "tp": 2.0,
      "trail": 0.5,
      "trail_after": 0.5,
      "dynamic": false
    }
  },
  {
    "annual": 26.633467089779227,
    "dd": 48.96202860984866,
    "win": 11.940298507462686,
    "pf": 16.443336435229316,
    "trades": 67,
    "total": 651.895534999091,
    "final": 75189.5534999091,
    "config": {
      "name": "ETH+ 动态仓位 + 止盈 300%",
      "stop": 0.05,
      "tp": 3.0,
      "trail": 0.5,
      "trail_after": 0.5,
      "dynamic": true
    }
  },
  {
    "annual": 9.971497800797247,
    "dd": 30.38355645094456,
    "win": 8.0,
    "pf": 28.354284325813683,
    "trades": 25,
    "total": 125.26345019385808,
    "final": 22526.345019385808,
    "config": {
      "name": "ETH+ 动态仓位 + 移动 80%",
      "stop": 0.05,
      "tp": null,
      "trail": 0.8,
      "trail_after": 0.8,
      "dynamic": true
    }
  },
  {
    "annual": 9.971497800797247,
    "dd": 30.38355645094456,
    "win": 8.0,
    "pf": 28.354284325813683,
    "trades": 25,
    "total": 125.26345019385808,
    "final": 22526.345019385808,
    "config": {
      "name": "ETH+ 固定仓位 + 移动 80%",
      "stop": 0.05,
      "tp": null,
      "trail": 0.8,
      "trail_after": 0.8,
      "dynamic": false
    }
  }
]